mangadownloadlib/MangaDownloadersContainer.py
mangadownloadlib/__init__.py
mangadownloadlib/registry.py
mangadownloadlib/downloaders/IMangaDownloader.py
mangadownloadlib/downloaders/MangaRequestsDownloader.py
mangadownloadlib/downloaders/StrategyProcessing.py
mangadownloadlib/downloaders/__init__.py
mangadownloadlib/downloaders/selenium/HoneyMangaDownloader.py
mangadownloadlib/downloaders/selenium/MangaDexDownloader.py
mangadownloadlib/downloaders/selenium/__init__.py
mangadownloadlib/downloaders/strategies/ArchiveStrategy.py
mangadownloadlib/downloaders/strategies/DeleteFolderStrategy.py
mangadownloadlib/downloaders/strategies/DeletePicturesStrategy.py
mangadownloadlib/downloaders/strategies/DownloadStrategy.py
mangadownloadlib/downloaders/strategies/MergeFramesStrategy.py
mangadownloadlib/downloaders/strategies/SavePDFStrategy.py
mangadownloadlib/downloaders/strategies/SavePSDStrategy.py
mangadownloadlib/downloaders/strategies/__init__.py
mangadownloadlib/entity/DownloaderData.py
mangadownloadlib/entity/MangaChapter.py
mangadownloadlib/entity/__init__.py
mangadownloadlib/enums/DownloadMode.py
mangadownloadlib/enums/__init__.py
mangadownloadlib/outils/Convertor.py
mangadownloadlib/outils/Counter.py
mangadownloadlib/outils/__init__.py
mangadownloadlib/parsers/BatoToParser.py
mangadownloadlib/parsers/KaoruHanaWarinToSakuParser.py
mangadownloadlib/parsers/MangaParserInterface.py
mangadownloadlib/parsers/XBatoParser.py
mangadownloadlib/parsers/__init__.py
mangadownloadlib-1.0.1.dist-info/METADATA
mangadownloadlib-1.0.1.dist-info/WHEEL
mangadownloadlib-1.0.1.dist-info/top_level.txt
mangadownloadlib-1.0.1.dist-info/RECORD
