Metadata-Version: 2.4
Name: mangadownloadlib
Version: 1.0.1
Summary: Python library to parse and download manga from the web
Home-page: https://github.com/NikitaVolya/MangaDownloader
Author: NikitaVolia
Author-email: volanskkijnikita2@gmail.com
License: MIT
Classifier: Development Status :: 3 - Alpha
Classifier: Intended Audience :: Developers
Classifier: Programming Language :: Python :: 3
Classifier: Topic :: Internet :: WWW/HTTP
Classifier: Topic :: Software Development :: Libraries
Classifier: Topic :: Utilities
Requires-Dist: attrs==25.4.0
Requires-Dist: beautifulsoup4==4.14.3
Requires-Dist: certifi==2026.1.4
Requires-Dist: cffi==2.0.0
Requires-Dist: charset-normalizer==3.4.4
Requires-Dist: Cython==3.2.4
Requires-Dist: Deprecated==1.3.1
Requires-Dist: docutils==0.22.4
Requires-Dist: h11==0.16.0
Requires-Dist: id==1.5.0
Requires-Dist: idna==3.11
Requires-Dist: img2pdf==0.6.3
Requires-Dist: jaraco.classes==3.4.0
Requires-Dist: jaraco.context==6.1.0
Requires-Dist: jaraco.functools==4.4.0
Requires-Dist: keyring==25.7.0
Requires-Dist: lxml==6.0.2
Requires-Dist: markdown-it-py==4.0.0
Requires-Dist: mdurl==0.1.2
Requires-Dist: more-itertools==10.8.0
Requires-Dist: nh3==0.3.2
Requires-Dist: numpy==2.4.1
Requires-Dist: outcome==1.3.0.post0
Requires-Dist: packaging==25.0
Requires-Dist: patool==4.0.3
Requires-Dist: pikepdf==10.2.0
Requires-Dist: pillow==12.1.0
Requires-Dist: pycparser==2.23
Requires-Dist: Pygments==2.19.2
Requires-Dist: PySocks==1.7.1
Requires-Dist: pytoshop==1.2.1
Requires-Dist: pywin32-ctypes==0.2.3
Requires-Dist: readme_renderer==44.0
Requires-Dist: requests==2.32.5
Requires-Dist: requests-toolbelt==1.0.0
Requires-Dist: rfc3986==2.0.0
Requires-Dist: rich==14.2.0
Requires-Dist: selenium==4.39.0
Requires-Dist: setuptools==80.9.0
Requires-Dist: sniffio==1.3.1
Requires-Dist: sortedcontainers==2.4.0
Requires-Dist: soupsieve==2.8.1
Requires-Dist: trio==0.32.0
Requires-Dist: trio-websocket==0.12.2
Requires-Dist: twine==6.2.0
Requires-Dist: typing_extensions==4.15.0
Requires-Dist: urllib3==2.6.3
Requires-Dist: websocket-client==1.9.0
Requires-Dist: wrapt==2.0.1
Requires-Dist: wsproto==1.3.2
Dynamic: author
Dynamic: author-email
Dynamic: classifier
Dynamic: description
Dynamic: description-content-type
Dynamic: home-page
Dynamic: license
Dynamic: requires-dist
Dynamic: summary
